<scenario id="S-1Q264ZD-1">
<domain>
   <issue type="integer" name="1" lowerbound="0" upperbound="8"/>
   <issue type="integer" name="2" lowerbound="0" upperbound="8"/>
</domain>
<profile id="A1" >
   <ufun>
      <CUBE height="54.0">
          <bound issue="1" min="8" max="8" />
          <bound issue="2" min="1" max="8" />
      </CUBE>
      <CUBE height="33.0">
          <bound issue="1" min="3" max="6" />
          <bound issue="2" min="0" max="7" />
      </CUBE>
      <CUBE height="4.0">
          <bound issue="1" min="1" max="2" />
      </CUBE>
      <CUBE height="99.0">
          <bound issue="2" min="1" max="4" />
      </CUBE>
   </ufun>
</profile>
<profile id="A2" >
   <ufun>
      <CUBE height="32.0">
          <bound issue="1" min="2" max="4" />
      </CUBE>
      <CUBE height="6.0">
          <bound issue="1" min="0" max="2" />
      </CUBE>
      <CUBE height="96.0">
          <bound issue="1" min="5" max="8" />
          <bound issue="2" min="6" max="8" />
      </CUBE>
      <CUBE height="64.0">
          <bound issue="1" min="2" max="6" />
          <bound issue="2" min="0" max="5" />
      </CUBE>
   </ufun>
</profile>
</scenario>
